pyqt_search_bar_menu/__init__.py
pyqt_search_bar_menu/searchBarMenu.py
pyqt_search_bar_menu-0.0.11.dist-info/LICENSE
pyqt_search_bar_menu-0.0.11.dist-info/METADATA
pyqt_search_bar_menu-0.0.11.dist-info/WHEEL
pyqt_search_bar_menu-0.0.11.dist-info/top_level.txt
pyqt_search_bar_menu-0.0.11.dist-info/RECORD
