Metadata-Version: 2.1
Name: pyqt-search-bar-menu
Version: 0.0.11
Summary: PyQt QMenu which contains search bar as first item
Home-page: https://github.com/yjg30737/pyqt-search-bar-menu.git
Author: Jung Gyu Yoon
Author-email: yjg30737@gmail.com
License: MIT
License-File: LICENSE
Requires-Dist: PyQt5 (>=5.8)
Requires-Dist: pyqt-instant-search-bar (>=0.0.1)
